kavy/__init__.py
kavy/core/__init__.py
kavy/core/kavy.py
kavy/modules/__init__.py
kavy/modules/get_api_key.py
kavy/modules/pdf_module.py
kavy/modules/txt_module.py
kavy/modules/url_module.py
kavy/modules/word_module.py
kavy/modules/write_api_key.py
kavy-1.0.3.dist-info/METADATA
kavy-1.0.3.dist-info/WHEEL
kavy-1.0.3.dist-info/RECORD
